Attachments/CLA/BTA_CLA_32.v
`timescale 1ns/1ps

module BTA_CLA_32#(parameter N=32, m=16)(input clk,input [(m*(N/8))-1:0]A,B,C,D,E,F,G,H, input C0,output [m+$clog2(N)-1:0]sum, output carry);

wire [N-1:0]c;
wire [((m+1)*(N/2))-1:0]s1;

//integer n=0;
//integer j;


BTA_CLA_16 a1(clk,A[(m*(N/8))-1:0],B[(m*(N/8))-1:0],C[(m*(N/8))-1:0],D[(m*(N/8))-1:0], C0,s1[m+$clog2(N/2)-1:0],c[0]);

BTA_CLA_16 a2(clk,E[(m*(N/8))-1:0],F[(m*(N/8))-1:0],G[(m*(N/8))-1:0],H[(m*(N/8))-1:0],C0,s1[2*m+7:m+$clog2(N/2)],c[1]);

CLA_20 a3(clk,s1[m+$clog2(N/2)-1:0],s1[2*m+7:m+$clog2(N/2)],C0,sum[m+$clog2(N)-1:0],carry);

endmodule

//////////////////////////////

`timescale 1ns/1ps

module BTA_CLA_16#(parameter N=16, m=16)(input clk,input [(m*(N/4))-1:0]A,B,C,D, input C0,output [m+$clog2(N)-1:0]sum, output carry);

wire [N-1:0]c;
wire [((m+1)*(N/2))-1:0]s1;

//integer n=0;
//integer j;


BTA_CLA_8 a1(clk,A[m-1:0],B[m-1:0],A[(2*m)-1:m],B[(2*m)-1:m],A[(3*m)-1:2*m],B[(3*m)-1:2*m],A[(4*m)-1:3*m],B[(4*m)-1:3*m],C0,s1[m+2:0],c[0]);

BTA_CLA_8 a2(clk,C[m-1:0],D[m-1:0],C[(2*m)-1:m],D[(2*m)-1:m],C[(3*m)-1:2*m],D[(3*m)-1:2*m],C[(4*m)-1:3*m],D[(4*m)-1:3*m],C0,s1[2*m+5:m+3],c[1]);

CLA_19 a3(clk,s1[m+2:0],s1[2*m+5:m+3],C0,sum[m+$clog2(N)-1:0],carry);

endmodule

////////////////////////////////

`timescale 1ns/1ps

module BTA_CLA_8 #(parameter N=8,m=16)(input clk,input [m-1:0]A,B,C,D,E,F,G,H, input C0,output [m+2:0]sum, output carry);
wire [N-1:0]c;
wire [105:0]s;

//1st stage -- N/2  -- here 4RCA's of each 16bits

CLA_16 a1(clk,A[m-1:0],B[m-1:0],C0,s[m:0],c[0]);
CLA_16 a2(clk,C[m-1:0],D[m-1:0],C0,s[m+17:m+1],c[1]);
CLA_16 a3(clk,E[m-1:0],F[m-1:0],C0,s[m+34:m+18],c[2]);
CLA_16 a4(clk,G[m-1:0],H[m-1:0],C0,s[m+51:m+35],c[3]);

//2nd stage --N/4 --here 2RCA's of each 17bits

CLA_17 a5(clk, s[m:0],s[m+17:m+1],C0, s[m+69:m+52],c[4]);
CLA_17 a6(clk, s[m+34:m+18],s[m+51:m+35],C0, s[m+87:m+70],c[5]);

// 3rd stage --N/8 --here 1RCA of 18bits

CLA_18 a7(clk, s[m+69:m+52],s[m+87:m+70],C0,sum[m+2:0],carry);

endmodule

/////////////////////////////////////

module CLA_16#(parameter m=16)(input clk,input [m-1:0]A, input [m-1:0]B,input C0, output [m:0]Sum, output Carry);
  reg [m-1:0]p, g;
  reg [m:0]c;
  wire [m-1:0]s;
  integer i;

always @(posedge clk)begin
c[0]=C0;
for(i=0;i<m;i=i+1)begin
p[i]=A[i]^B[i];
g[i]=A[i]&B[i];
c[i+1]=(c[i]&p[i]) + g[i];
end
end

genvar j;
generate 
for(j=0;j<m;j=j+1)begin
add a1(p[j],c[j],s[j]);

end
endgenerate
assign Carry = c[m];
assign Sum ={c[m],s[m-1:0]};

endmodule


//module add(input P,C,output sum);

//assign sum=P^C;
//endmodule

/////////////////////

module CLA_17#(parameter m=17)(input clk,input [m-1:0]A, input [m-1:0]B,input C0, output [m:0]Sum, output Carry);
  reg [m-1:0]p, g;
  reg [m:0]c;
  wire [m-1:0]s;
  integer i;

always @(posedge clk)begin
c[0]=C0;
for(i=0;i<m;i=i+1)begin
p[i]=A[i]^B[i];
g[i]=A[i]&B[i];
c[i+1]=(c[i]&p[i]) + g[i];
end
end

genvar j;
generate 
for(j=0;j<m;j=j+1)begin
add a1(p[j],c[j],s[j]);

end
endgenerate
assign Carry = c[m];
assign Sum ={c[m],s[m-1:0]};

endmodule


//module add(input P,C,output sum);

//assign sum=P^C;
//endmodule
/////////////////////////////

module CLA_18#(parameter m=18)(input clk,input [m-1:0]A, input [m-1:0]B,input C0, output [m:0]Sum, output Carry);
  reg [m-1:0]p, g;
  reg [m:0]c;
  wire [m-1:0]s;
  integer i;

always @(posedge clk)begin
c[0]=C0;
for(i=0;i<m;i=i+1)begin
p[i]=A[i]^B[i];
g[i]=A[i]&B[i];
c[i+1]=(c[i]&p[i]) + g[i];
end
end

genvar j;
generate 
for(j=0;j<m;j=j+1)begin
add a1(p[j],c[j],s[j]);

end
endgenerate
assign Carry = c[m];
assign Sum ={c[m],s[m-1:0]};

endmodule

////////////////////////////

module CLA_19#(parameter m=19)(input clk,input [m-1:0]A, input [m-1:0]B,input C0, output [m:0]Sum, output Carry);
  reg [m-1:0]p, g;
  reg [m:0]c;
  wire [m-1:0]s;
  integer i;

always @(posedge clk)begin
c[0]=C0;
for(i=0;i<m;i=i+1)begin
p[i]=A[i]^B[i];
g[i]=A[i]&B[i];
c[i+1]=(c[i]&p[i]) + g[i];
end
end

genvar j;
generate 
for(j=0;j<m;j=j+1)begin
add a1(p[j],c[j],s[j]);

end
endgenerate
assign Carry = c[m];
assign Sum ={c[m],s[m-1:0]};

endmodule


/////////////////////////////////

module CLA_20#(parameter m=20)(input clk,input [m-1:0]A, input [m-1:0]B,input C0, output [m:0]Sum, output Carry);
  reg [m-1:0]p, g;
  reg [m:0]c;
  wire [m-1:0]s;
  integer i;

always @(posedge clk)begin
c[0]=C0;
for(i=0;i<m;i=i+1)begin
p[i]=A[i]^B[i];
g[i]=A[i]&B[i];
c[i+1]=(c[i]&p[i]) + g[i];
end
end

genvar j;
generate 
for(j=0;j<m;j=j+1)begin
add a1(p[j],c[j],s[j]);

end
endgenerate
assign Carry = c[m];
assign Sum ={c[m],s[m-1:0]};

endmodule
/////////////////////////////////

module add(input P,C,output sum);

assign sum=P^C;
endmodule

Attachments/CLA/CLA_16bit_tb.v
module CLA_16bit_tb#(parameter N=17);
reg clk;
reg [N-1:0]A;
reg [N-1:0]B;
reg C0;
wire [N:0]sum;
wire carry;

CLA_16 a1(clk,A,B,C0,sum,carry);

//initial repeat(255) #10 {A,B} = {A,B} + 8'b1;


initial begin

$dumpfile("CLA_16bit.vcd");
$dumpvars(0,CLA_16bit_tb);
end

initial begin
clk=0;
A=17'b0; B=17'b0; C0=0;
#20 A=17'b01101111000111010; B=17'b01111000010101110;
//#20 A=16'b1110111010101101; B=16'b0010101001101110;
//#20 A=16'b1101010111011011; B=16'b1111111111111111;
#100 $finish;

end


always begin
#1 clk=~clk;
end

endmodule

Attachments/CLA/CLA_16bit.vcd
$date
	Wed Nov 22 00:17:58 2023
$end
$version
	Icarus Verilog
$end
$timescale
	1s
$end
$scope module CLA_16bit_tb $end
$var wire 18 ! sum [17:0] $end
$var wire 1 " carry $end
$var reg 17 # A [16:0] $end
$var reg 17 $ B [16:0] $end
$var reg 1 % C0 $end
$var reg 1 & clk $end
$scope module a1 $end
$var wire 17 ' A [16:0] $end
$var wire 17 ( B [16:0] $end
$var wire 1 % C0 $end
$var wire 1 & clk $end
$var wire 17 ) s [16:0] $end
$var wire 18 * Sum [17:0] $end
$var wire 1 " Carry $end
$var reg 18 + c [17:0] $end
$var reg 17 , g [16:0] $end
$var reg 17 - p [16:0] $end
$var integer 32 . i [31:0] $end
$scope begin genblk1[0] $end
$scope module a1 $end
$var wire 1 / C $end
$var wire 1 0 P $end
$var wire 1 1 sum $end
$upscope $end
$upscope $end
$scope begin genblk1[1] $end
$scope module a1 $end
$var wire 1 2 C $end
$var wire 1 3 P $end
$var wire 1 4 sum $end
$upscope $end
$upscope $end
$scope begin genblk1[2] $end
$scope module a1 $end
$var wire 1 5 C $end
$var wire 1 6 P $end
$var wire 1 7 sum $end
$upscope $end
$upscope $end
$scope begin genblk1[3] $end
$scope module a1 $end
$var wire 1 8 C $end
$var wire 1 9 P $end
$var wire 1 : sum $end
$upscope $end
$upscope $end
$scope begin genblk1[4] $end
$scope module a1 $end
$var wire 1 ; C $end
$var wire 1 < P $end
$var wire 1 = sum $end
$upscope $end
$upscope $end
$scope begin genblk1[5] $end
$scope module a1 $end
$var wire 1 > C $end
$var wire 1 ? P $end
$var wire 1 @ sum $end
$upscope $end
$upscope $end
$scope begin genblk1[6] $end
$scope module a1 $end
$var wire 1 A C $end
$var wire 1 B P $end
$var wire 1 C sum $end
$upscope $end
$upscope $end
$scope begin genblk1[7] $end
$scope module a1 $end
$var wire 1 D C $end
$var wire 1 E P $end
$var wire 1 F sum $end
$upscope $end
$upscope $end
$scope begin genblk1[8] $end
$scope module a1 $end
$var wire 1 G C $end
$var wire 1 H P $end
$var wire 1 I sum $end
$upscope $end
$upscope $end
$scope begin genblk1[9] $end
$scope module a1 $end
$var wire 1 J C $end
$var wire 1 K P $end
$var wire 1 L sum $end
$upscope $end
$upscope $end
$scope begin genblk1[10] $end
$scope module a1 $end
$var wire 1 M C $end
$var wire 1 N P $end
$var wire 1 O sum $end
$upscope $end
$upscope $end
$scope begin genblk1[11] $end
$scope module a1 $end
$var wire 1 P C $end
$var wire 1 Q P $end
$var wire 1 R sum $end
$upscope $end
$upscope $end
$scope begin genblk1[12] $end
$scope module a1 $end
$var wire 1 S C $end
$var wire 1 T P $end
$var wire 1 U sum $end
$upscope $end
$upscope $end
$scope begin genblk1[13] $end
$scope module a1 $end
$var wire 1 V C $end
$var wire 1 W P $end
$var wire 1 X sum $end
$upscope $end
$upscope $end
$scope begin genblk1[14] $end
$scope module a1 $end
$var wire 1 Y C $end
$var wire 1 Z P $end
$var wire 1 [ sum $end
$upscope $end
$upscope $end
$scope begin genblk1[15] $end
$scope module a1 $end
$var wire 1 \ C $end
$var wire 1 ] P $end
$var wire 1 ^ sum $end
$upscope $end
$upscope $end
$scope begin genblk1[16] $end
$scope module a1 $end
$var wire 1 _ C $end
$var wire 1 ` P $end
$var wire 1 a sum $end
$upscope $end
$upscope $end
$upscope $end
$upscope $end
$enddefinitions $end
#0
$dumpvars
xa
x`
x_
x^
x]
x\
x[
xZ
xY
xX
xW
xV
xU
xT
xS
xR
xQ
xP
xO
xN
xM
xL
xK
xJ
xI
xH
xG
xF
xE
xD
xC
xB
xA
x@
x?
x>
x=
x<
x;
x:
x9
x8
x7
x6
x5
x4
x3
x2
x1
x0
x/
bx .
bx -
bx ,
bx +
bx *
bx )
b0 (
b0 '
0&
0%
b0 $
b0 #
x"
bx !
$end
#1
0a
0^
0[
0X
0U
0R
0O
0L
0I
0F
0C
0@
0=
0:
07
04
b0 )
01
0"
b0 !
b0 *
0`
0_
0]
0\
0Z
0Y
0W
0V
0T
0S
0Q
0P
0N
0M
0K
0J
0H
0G
0E
0D
0B
0A
0?
0>
0<
0;
09
08
06
05
03
02
00
0/
b0 ,
b0 -
b10001 .
b0 +
1&
#2
0&
#3
b10001 .
1&
#4
0&
#5
b10001 .
1&
#6
0&
#7
b10001 .
1&
#8
0&
#9
b10001 .
1&
#10
0&
#11
b10001 .
1&
#12
0&
#13
b10001 .
1&
#14
0&
#15
b10001 .
1&
#16
0&
#17
b10001 .
1&
#18
0&
#19
b10001 .
1&
#20
0&
b1111000010101110 $
b1111000010101110 (
b1101111000111010 #
b1101111000111010 '
#21
1a
1^
1[
1R
1O
1L
1F
1C
1@
b11100111011101000 !
b11100111011101000 *
b11100111011101000 )
1:
1_
1\
1Y
1W
1V
1Q
1N
1K
1E
1A
1>
1<
1;
18
16
15
b10111010010100 -
b11110000001111100 +
b1101000000101010 ,
b10001 .
1&
#22
0&
#23
b10001 .
1&
#24
0&
#25
b10001 .
1&
#26
0&
#27
b10001 .
1&
#28
0&
#29
b10001 .
1&
#30
0&
#31
b10001 .
1&
#32
0&
#33
b10001 .
1&
#34
0&
#35
b10001 .
1&
#36
0&
#37
b10001 .
1&
#38
0&
#39
b10001 .
1&
#40
0&
#41
b10001 .
1&
#42
0&
#43
b10001 .
1&
#44
0&
#45
b10001 .
1&
#46
0&
#47
b10001 .
1&
#48
0&
#49
b10001 .
1&
#50
0&
#51
b10001 .
1&
#52
0&
#53
b10001 .
1&
#54
0&
#55
b10001 .
1&
#56
0&
#57
b10001 .
1&
#58
0&
#59
b10001 .
1&
#60
0&
#61
b10001 .
1&
#62
0&
#63
b10001 .
1&
#64
0&
#65
b10001 .
1&
#66
0&
#67
b10001 .
1&
#68
0&
#69
b10001 .
1&
#70
0&
#71
b10001 .
1&
#72
0&
#73
b10001 .
1&
#74
0&
#75
b10001 .
1&
#76
0&
#77
b10001 .
1&
#78
0&
#79
b10001 .
1&
#80
0&
#81
b10001 .
1&
#82
0&
#83
b10001 .
1&
#84
0&
#85
b10001 .
1&
#86
0&
#87
b10001 .
1&
#88
0&
#89
b10001 .
1&
#90
0&
#91
b10001 .
1&
#92
0&
#93
b10001 .
1&
#94
0&
#95
b10001 .
1&
#96
0&
#97
b10001 .
1&
#98
0&
#99
b10001 .
1&
#100
0&
#101
b10001 .
1&
#102
0&
#103
b10001 .
1&
#104
0&
#105
b10001 .
1&
#106
0&
#107
b10001 .
1&
#108
0&
#109
b10001 .
1&
#110
0&
#111
b10001 .
1&
#112
0&
#113
b10001 .
1&
#114
0&
#115
b10001 .
1&
#116
0&
#117
b10001 .
1&
#118
0&
#119
b10001 .
1&
